adjacent_correlation_analysis/__init__.py
adjacent_correlation_analysis/analysis.py
adjacent_correlation_analysis/plotting.py
adjacent_correlation_analysis-0.1.1.dist-info/LICENSE.md
adjacent_correlation_analysis-0.1.1.dist-info/METADATA
adjacent_correlation_analysis-0.1.1.dist-info/WHEEL
adjacent_correlation_analysis-0.1.1.dist-info/RECORD
