Metadata-Version: 2.3
Name: adjacent-correlation-analysis
Version: 0.1.1
Summary: A python package to reveal regularites from complex image data using correlations
License: BSD
Author: Guang-Xing Li
Author-email: ligx.ngc7293@gmail.com
Requires-Python: >=3.0
Classifier: License :: Other/Proprietary License
Classifier: Programming Language :: Python :: 3
Classifier: Programming Language :: Python :: 3.4
Classifier: Programming Language :: Python :: 3.5
Classifier: Programming Language :: Python :: 3.6
Classifier: Programming Language :: Python :: 3.7
Classifier: Programming Language :: Python :: 3.8
Classifier: Programming Language :: Python :: 3.9
Classifier: Programming Language :: Python :: 3.10
Classifier: Programming Language :: Python :: 3.11
Classifier: Programming Language :: Python :: 3.12
Classifier: Programming Language :: Python :: 3.13
Requires-Dist: matplotlib
Requires-Dist: numpy
Requires-Dist: scipy
Project-URL: Bug Tracker, https://github.com/yourusername/adjacent_correlation_analysis/issues
Project-URL: Homepage, https://github.com/yourusername/adjacent_correlation_analysis
